{
  "usableSessionsCount": 5,
  "retiredSessionsCount": 0,
  "sessions": [
    {
      "id": "session_BlL0VyhkTn",
      "cookieJar": {
        "version": "tough-cookie@5.1.2",
        "storeType": "MemoryCookieStore",
        "rejectPublicSuffixes": true,
        "enableLooseMode": false,
        "allowSpecialUseDomain": true,
        "prefixSecurity": "silent",
        "cookies": [
          {
            "key": "AWSALBTG",
            "value": "Npx3KM4nh8yoNTsrl8sHQoN+zJPemhOwbFYEFnm6O6CGJWyiC533d4jRnKjzoqXTJiIZ1ZlO0t77TmSZlVacM/BBNmUVFttLfOUr6VE+Pa1EnSnNjPJ83QmDTT/cKwdkVEDtGbCS4cxaftDjozp9t6Ia8JounSYEONKS8hSVSuBM",
            "expires": "2025-08-16T11:34:29.000Z",
            "domain": "www.businessinsider.com",
            "path": "/",
            "hostOnly": true,
            "creation": "2025-08-09T11:36:37.900Z",
            "lastAccessed": "2025-08-09T11:36:37.900Z"
          },
          {
            "key": "AWSALBTGCORS",
            "value": "Npx3KM4nh8yoNTsrl8sHQoN+zJPemhOwbFYEFnm6O6CGJWyiC533d4jRnKjzoqXTJiIZ1ZlO0t77TmSZlVacM/BBNmUVFttLfOUr6VE+Pa1EnSnNjPJ83QmDTT/cKwdkVEDtGbCS4cxaftDjozp9t6Ia8JounSYEONKS8hSVSuBM",
            "expires": "2025-08-16T11:34:29.000Z",
            "domain": "www.businessinsider.com",
            "path": "/",
            "secure": true,
            "hostOnly": true,
            "creation": "2025-08-09T11:36:37.900Z",
            "lastAccessed": "2025-08-09T11:36:37.900Z",
            "sameSite": "none"
          }
        ]
      },
      "userData": {},
      "maxErrorScore": 3,
      "errorScoreDecrement": 0.5,
      "expiresAt": "2025-08-09T12:26:36.168Z",
      "createdAt": "2025-08-09T11:36:36.168Z",
      "usageCount": 1,
      "maxUsageCount": 50,
      "errorScore": 0
    },
    {
      "id": "session_GxQfdULV1p",
      "cookieJar": {
        "version": "tough-cookie@5.1.2",
        "storeType": "MemoryCookieStore",
        "rejectPublicSuffixes": true,
        "enableLooseMode": false,
        "allowSpecialUseDomain": true,
        "prefixSecurity": "silent",
        "cookies": [
          {
            "key": "AWSALBTG",
            "value": "M/Xt7YRzl15E/8c3ATV01+lg5HX12XkVG2jHFKBDxnMrq8xRz4maAP7fFdHs83TcmF2KW/axAvMMCldefcu5LTbtztDbjSV45cT2ZFLI2j42hIGVlfPAcUNdKN4XooSYOr+FN76ECrmSXc8lTz/lLKyK4wzT6IZaIAmtU75DLvo8",
            "expires": "2025-08-16T11:19:48.000Z",
            "domain": "www.businessinsider.com",
            "path": "/",
            "hostOnly": true,
            "creation": "2025-08-09T11:36:39.182Z",
            "lastAccessed": "2025-08-09T11:36:39.182Z"
          },
          {
            "key": "AWSALBTGCORS",
            "value": "M/Xt7YRzl15E/8c3ATV01+lg5HX12XkVG2jHFKBDxnMrq8xRz4maAP7fFdHs83TcmF2KW/axAvMMCldefcu5LTbtztDbjSV45cT2ZFLI2j42hIGVlfPAcUNdKN4XooSYOr+FN76ECrmSXc8lTz/lLKyK4wzT6IZaIAmtU75DLvo8",
            "expires": "2025-08-16T11:19:48.000Z",
            "domain": "www.businessinsider.com",
            "path": "/",
            "secure": true,
            "hostOnly": true,
            "creation": "2025-08-09T11:36:39.183Z",
            "lastAccessed": "2025-08-09T11:36:39.183Z",
            "sameSite": "none"
          }
        ]
      },
      "userData": {},
      "maxErrorScore": 3,
      "errorScoreDecrement": 0.5,
      "expiresAt": "2025-08-09T12:26:38.069Z",
      "createdAt": "2025-08-09T11:36:38.069Z",
      "usageCount": 1,
      "maxUsageCount": 50,
      "errorScore": 0
    },
    {
      "id": "session_bbav34rfpU",
      "cookieJar": {
        "version": "tough-cookie@5.1.2",
        "storeType": "MemoryCookieStore",
        "rejectPublicSuffixes": true,
        "enableLooseMode": false,
        "allowSpecialUseDomain": true,
        "prefixSecurity": "silent",
        "cookies": [
          {
            "key": "AWSALBTG",
            "value": "MVSRpAdOIAFzNbM3GUW2HIiPPKDgrhj20I98PhBRKHCUUttigKkAlmiewbb2Tj3EoW4/VYfzNITR933umT+msxzNwlnyq/K6ctoJsKM1RCfVIqah0soonG+DcLfFoDARPiA7Hly6kVE7PvgQlLM7gnbQ06/GBy2i1txxG/Ye6g49",
            "expires": "2025-08-15T19:49:47.000Z",
            "domain": "www.businessinsider.com",
            "path": "/",
            "hostOnly": true,
            "creation": "2025-08-09T11:36:39.207Z",
            "lastAccessed": "2025-08-09T11:36:39.207Z"
          },
          {
            "key": "AWSALBTGCORS",
            "value": "MVSRpAdOIAFzNbM3GUW2HIiPPKDgrhj20I98PhBRKHCUUttigKkAlmiewbb2Tj3EoW4/VYfzNITR933umT+msxzNwlnyq/K6ctoJsKM1RCfVIqah0soonG+DcLfFoDARPiA7Hly6kVE7PvgQlLM7gnbQ06/GBy2i1txxG/Ye6g49",
            "expires": "2025-08-15T19:49:47.000Z",
            "domain": "www.businessinsider.com",
            "path": "/",
            "secure": true,
            "hostOnly": true,
            "creation": "2025-08-09T11:36:39.207Z",
            "lastAccessed": "2025-08-09T11:36:39.207Z",
            "sameSite": "none"
          }
        ]
      },
      "userData": {},
      "maxErrorScore": 3,
      "errorScoreDecrement": 0.5,
      "expiresAt": "2025-08-09T12:26:38.072Z",
      "createdAt": "2025-08-09T11:36:38.072Z",
      "usageCount": 1,
      "maxUsageCount": 50,
      "errorScore": 0
    },
    {
      "id": "session_Fz80UzVQvU",
      "cookieJar": {
        "version": "tough-cookie@5.1.2",
        "storeType": "MemoryCookieStore",
        "rejectPublicSuffixes": true,
        "enableLooseMode": false,
        "allowSpecialUseDomain": true,
        "prefixSecurity": "silent",
        "cookies": [
          {
            "key": "AWSALBTG",
            "value": "1r2FDJ2h71Z9JavELmB1DMdcZO5JIsdrhI2sjlxNcwV5JzMO7FEH9QF59huoZVKprPEFbyToc8FtiyfQZe81WB2iriv5NkjZ82dK89GHd7EB0FkuHhX3mtknzl2J3dJmHHwtBnRplv4+Wsme6adhjIwhLvSPqMe8jKldTB22TYqQ",
            "expires": "2025-08-15T19:34:22.000Z",
            "domain": "www.businessinsider.com",
            "path": "/",
            "hostOnly": true,
            "creation": "2025-08-09T11:36:40.267Z",
            "lastAccessed": "2025-08-09T11:36:40.267Z"
          },
          {
            "key": "AWSALBTGCORS",
            "value": "1r2FDJ2h71Z9JavELmB1DMdcZO5JIsdrhI2sjlxNcwV5JzMO7FEH9QF59huoZVKprPEFbyToc8FtiyfQZe81WB2iriv5NkjZ82dK89GHd7EB0FkuHhX3mtknzl2J3dJmHHwtBnRplv4+Wsme6adhjIwhLvSPqMe8jKldTB22TYqQ",
            "expires": "2025-08-15T19:34:22.000Z",
            "domain": "www.businessinsider.com",
            "path": "/",
            "secure": true,
            "hostOnly": true,
            "creation": "2025-08-09T11:36:40.267Z",
            "lastAccessed": "2025-08-09T11:36:40.267Z",
            "sameSite": "none"
          }
        ]
      },
      "userData": {},
      "maxErrorScore": 3,
      "errorScoreDecrement": 0.5,
      "expiresAt": "2025-08-09T12:26:39.222Z",
      "createdAt": "2025-08-09T11:36:39.222Z",
      "usageCount": 1,
      "maxUsageCount": 50,
      "errorScore": 0
    },
    {
      "id": "session_NaufeopQdh",
      "cookieJar": {
        "version": "tough-cookie@5.1.2",
        "storeType": "MemoryCookieStore",
        "rejectPublicSuffixes": true,
        "enableLooseMode": false,
        "allowSpecialUseDomain": true,
        "prefixSecurity": "silent",
        "cookies": [
          {
            "key": "AWSALBTG",
            "value": "df9DD7X33PH5b7IIJIZKQO0F6eDHm4FdcV4M8xkKr1dR05RX5Zb5bDaIoAMl+WwGsG0vvwm/lxVyytVGpG53pfDDPuzXLA7eVLyVGxqfHaXY78OppAAROb91eC43nQRho7Rg+Fag+wJZ9O+cqSKRtl6n+2GV0ytm1RUFxPkD2tH8",
            "expires": "2025-08-15T19:37:23.000Z",
            "domain": "www.businessinsider.com",
            "path": "/",
            "hostOnly": true,
            "creation": "2025-08-09T11:36:40.286Z",
            "lastAccessed": "2025-08-09T11:36:40.286Z"
          },
          {
            "key": "AWSALBTGCORS",
            "value": "df9DD7X33PH5b7IIJIZKQO0F6eDHm4FdcV4M8xkKr1dR05RX5Zb5bDaIoAMl+WwGsG0vvwm/lxVyytVGpG53pfDDPuzXLA7eVLyVGxqfHaXY78OppAAROb91eC43nQRho7Rg+Fag+wJZ9O+cqSKRtl6n+2GV0ytm1RUFxPkD2tH8",
            "expires": "2025-08-15T19:37:23.000Z",
            "domain": "www.businessinsider.com",
            "path": "/",
            "secure": true,
            "hostOnly": true,
            "creation": "2025-08-09T11:36:40.286Z",
            "lastAccessed": "2025-08-09T11:36:40.286Z",
            "sameSite": "none"
          }
        ]
      },
      "userData": {},
      "maxErrorScore": 3,
      "errorScoreDecrement": 0.5,
      "expiresAt": "2025-08-09T12:26:39.233Z",
      "createdAt": "2025-08-09T11:36:39.233Z",
      "usageCount": 1,
      "maxUsageCount": 50,
      "errorScore": 0
    }
  ]
}